PivotalTrackerScraper
