Metadata-Version: 1.0
Name: jenkins-pivotaltrackerscraper
Version: 5.5.0
Summary: Pivotal Tracker Scraper for Jenkins
Home-page: https://github.com/KMK-ONLINE/PivotalTrackerScraper
Author: Henry Xu
Author-email: hxu@bbmtek.com
License: MIT
Platform: UNKNOWN
